LICENSE
MANIFEST.in
README.md
setup.py
etc/osidle-notify
etc/osidled-virsh.conf
etc/osidled.conf
etc/systemd/system/osidled-virsh.service
etc/systemd/system/osidled.service
osidle/__init__.py
osidle/analysis.py
osidle/common.py
osidle/configuration.py
osidle/dataseries.py
osidle/monitor.py
osidle/osconnect.py
osidle/packdb.py
osidle/rawdata.py
osidle/runcommand.py
osidle/storage.py
osidle/version.py
osidle/virsh2osidle.py
osidle.egg-info/PKG-INFO
osidle.egg-info/SOURCES.txt
osidle.egg-info/dependency_links.txt
osidle.egg-info/entry_points.txt
osidle.egg-info/requires.txt
osidle.egg-info/top_level.txt