Metadata-Version: 2.1
Name: osidle
Version: 1.2.3
Summary: A system that gathers information for the usage of resources of the VMs in OpenStack, to try to detect which of them are idle
Home-page: https://github.com/grycap/osidle
Author: Carlos A.
Author-email: caralla@upv.es
License: Apache 2.0
Keywords: openstack,idle,virtual machine
Classifier: Development Status :: 4 - Beta
Classifier: Intended Audience :: System Administrators
Classifier: Topic :: Utilities
Classifier: License :: OSI Approved :: Apache Software License
Classifier: Programming Language :: Python :: 3
License-File: LICENSE
